Metadata-Version: 1.0
Name: rajjr-probability
Version: 1.0
Summary: Gaussian and Binomial distributions
Home-page: UNKNOWN
Author: Robert Johnson
Author-email: info@junkmail.com
License: UNKNOWN
Platform: UNKNOWN
